zapnet/__init__.py
zapnet/cli.py
zapnet/tcp_engine.py
zapnet/udp_engine.py
zapnet/utils/__init__.py
zapnet/utils/errors.py
zapnet/utils/logger.py
zapnet/utils/network.py
zapnet/utils/parser.py
zapnet-0.1.1.dist-info/LICENSE
zapnet-0.1.1.dist-info/METADATA
zapnet-0.1.1.dist-info/WHEEL
zapnet-0.1.1.dist-info/entry_points.txt
zapnet-0.1.1.dist-info/RECORD
