Metadata-Version: 2.1
Name: zapnet
Version: 0.1.1
Summary: Network diagnostics toolkit
Home-page: https://github.com/luhuadong/zapnet
License: MIT
Author: luhuadong
Author-email: luhuadong@163.com
Requires-Python: >=3.6,<4.0
Classifier: License :: OSI Approved :: MIT License
Classifier: Programming Language :: Python :: 3
Classifier: Programming Language :: Python :: 3.6
Classifier: Programming Language :: Python :: 3.7
Classifier: Programming Language :: Python :: 3.8
Classifier: Programming Language :: Python :: 3.9
Classifier: Programming Language :: Python :: 3.10
Classifier: Programming Language :: Python :: 3.11
Classifier: Programming Language :: Python :: 3.12
Classifier: Programming Language :: Python :: 3.13
Requires-Dist: click (>=8.1.3,<9.0.0)
Requires-Dist: netifaces (>=0.11.0,<0.12.0)
Project-URL: Repository, https://github.com/luhuadong/zapnet
